[{
    "number": "1",
    "name": "12th Street Ballfield",
    "city": "Nashville",
    "state": "TN",
    "zip": "",
    "location": ["36.25881976500045", "-86.64963669099967"],
    "address": "1201 Elliston St"
},{
    "number": "2",
    "name": "Alvin G. Beaman Park",
    "city": "Nashville",
    "state": "TN",
    "zip": "",
    "location": ["36.262468", "-86.894281"],
    "address": "5911 Old Hickory Blvd."
},{
    "number": "3",
    "name": "Antioch Park",
    "city": "Nashville",
    "state": "TN",
    "zip": "",
    "location": ["36.055703", "-86.672911"],
    "address": "5023 Blue Hole Rd"
},{
    "number": "4",
    "name": "Bass Park",
    "city": "Nashville",
    "state": "TN",
    "zip": "",
    "location": ["36.175144", "-86.741637"],
    "address": "1604 Holly St"
},{
    "number": "5",
    "name": "Bellevue Park",
    "city": "Nashville",
    "state": "TN",
    "zip": "",
    "location": ["36.072052", "-86.934547"],
    "address": "656 Colice Jeanne Rd"
},{
    "number": "6",
    "name": "Bells Bend Park",
    "city": "Nashville",
    "state": "TN",
    "zip": "",
    "location": ["36.154279", "-86.921868"],
    "address": "4187 Old Hickory Blvd"
},{
    "number": "7",
    "name": "Bicentennial Park",
    "city": "Nashville",
    "state": "TN",
    "zip": "",
    "location": ["36.16399329900048", "-86.77543807099966"],
    "address": "170 1st Ave N"
},{
    "number": "8",
    "name": "Bordeaux Garden Park",
    "city": "Nashville",
    "state": "TN",
    "zip": "",
    "location": ["36.179714", "-86.839548"],
    "address": "Snell Blvd, at Panorama Dr"
},{
    "number": "9",
    "name": "Bordeaux-Timothy Drive Park",
    "city": "Nashville",
    "state": "TN",
    "zip": "",
    "location": ["36.214358", "-86.843486"],
    "address": "4100 Timothy Dr"
},{
    "number": "10",
    "name": "Brookmeade Park",
    "city": "Nashville",
    "state": "TN",
    "zip": "",
    "location": ["36.12937732900048", "-86.90413793099964"],
    "address": "7002 Charlotte Pike"
},{
    "number": "11",
    "name": "Buena Vista Park",
    "city": "Nashville",
    "state": "TN",
    "zip": "",
    "location": ["36.16784292800048", "-86.77815577199965"],
    "address": "2301 Metro Center Blvd."
},{
    "number": "12",
    "name": "Cane Ridge Park",
    "city": "Nashville",
    "state": "TN",
    "zip": "",
    "location": ["35.991359", "-86.622522"],
    "address": "419 Battle Rd"
},{
    "number": "13",
    "name": "Cecil Rhea Crawford Park",
    "city": "Nashville",
    "state": "TN",
    "zip": "",
    "location": ["36.00143217000044", "-86.63680479799967"],
    "address": "6043 Cane Ridge Rd"
},{
    "number": "14",
    "name": "Cedar Hill",
    "city": "Nashville",
    "state": "TN",
    "zip": "",
    "location": ["36.271773", "-86.748127"],
    "address": "860 West Old Hickory Blvd"
},{
    "number": "15",
    "name": "Centennial Park",
    "city": "Nashville",
    "state": "TN",
    "zip": "",
    "location": ["36.149721", "-86.813319"],
    "address": "2500 West End Ave"
},{
    "number": "16",
    "name": "Charlotte Park",
    "city": "Nashville",
    "state": "TN",
    "zip": "",
    "location": ["36.154546", "-86.870581"],
    "address": "6031 Deal Ave"
},{
    "number": "17",
    "name": "Church Street Park",
    "city": "Nashville",
    "state": "TN",
    "zip": "",
    "location": ["36.162692", "-86.781812"],
    "address": "600 Church St"
},{
    "number": "18",
    "name": "Cleveland Park",
    "city": "Nashville",
    "state": "TN",
    "zip": "",
    "location": ["36.187500", "-86.761563"],
    "address": "925 N 6th St"
},{
    "number": "19",
    "name": "Clinton B. Fisk Park",
    "city": "Nashville",
    "state": "TN",
    "zip": "",
    "location": ["36.17400500100047", "-86.81580211799968"],
    "address": "2410 Burch St"
},{
    "number": "20",
    "name": "Commerce Center Park",
    "city": "Nashville",
    "state": "TN",
    "zip": "",
    "location": ["36.162224", "-86.776107"],
    "address": "120 3rd Ave N"
},{
    "number": "21",
    "name": "County Cemetery",
    "city": "Nashville",
    "state": "TN",
    "zip": "",
    "location": ["36.18292398500046", "-86.84984572999969"],
    "address": "1398 County Hospital Road"
},{
    "number": "22",
    "name": "Crooked Branch Park",
    "city": "Nashville",
    "state": "TN",
    "zip": "",
    "location": ["36.24124583300045", "-86.64080446699967"],
    "address": "116D Ray Ave"
},{
    "number": "23",
    "name": "Cumberland Park",
    "city": "Nashville",
    "state": "TN",
    "zip": "",
    "location": ["36.162705", "-86.768597"],
    "address": "592 South 1st Street"
},{
    "number": "24",
    "name": "Dallas H. Neil Park",
    "city": "Nashville",
    "state": "TN",
    "zip": "",
    "location": ["36.134456", "-86.777987"],
    "address": "1910 8th Ave South"
},{
    "number": "25",
    "name": "E. N. Peeler Park",
    "city": "Nashville",
    "state": "TN",
    "zip": "",
    "location": ["36.200208", "-86.654167"],
    "address": "2043 Neelys Bend Rd"
},{
    "number": "26",
    "name": "E. S. Rose Park",
    "city": "Nashville",
    "state": "TN",
    "zip": "",
    "location": ["36.143275", "-86.783224"],
    "address": "1000 Edgehill Ave"
},{
    "number": "27",
    "name": "East Bank Greenway",
    "city": "Nashville",
    "state": "TN",
    "zip": "",
    "location": ["36.16438323800048", "-86.77235099799964"],
    "address": "2 Titans Way"
},{
    "number": "28",
    "name": "East Park",
    "city": "Nashville",
    "state": "TN",
    "zip": "",
    "location": ["36.173515", "-86.760312"],
    "address": "700 Woodland St"
},{
    "number": "29",
    "name": "Eastland Park",
    "city": "Nashville",
    "state": "TN",
    "zip": "",
    "location": ["36.192151", "-86.739673"],
    "address": "1501 Douglas Ave"
},{
    "number": "30",
    "name": "Edwin Warner Park",
    "city": "Nashville",
    "state": "TN",
    "zip": "",
    "location": ["36.053264", "-86.899698"],
    "address": "50 Vaughn Rd"
},{
    "number": "31",
    "name": "Elizabeth Park",
    "city": "Nashville",
    "state": "TN",
    "zip": "",
    "location": ["36.178367", "-86.802446"],
    "address": "1701 Arthur Ave"
},{
    "number": "32",
    "name": "Elmington Park",
    "city": "Nashville",
    "state": "TN",
    "zip": "",
    "location": ["36.133568", "-86.824021"],
    "address": "3531 West End Ave"
},{
    "number": "33",
    "name": "England Park",
    "city": "Nashville",
    "state": "TN",
    "zip": "",
    "location": ["36.156487", "-86.854978"],
    "address": "811 Delray Dr"
},{
    "number": "34",
    "name": "Ezell Road Park",
    "city": "Nashville",
    "state": "TN",
    "zip": "",
    "location": ["36.088520", "-86.680980"],
    "address": "5135 Harding Pl"
},{
    "number": "35",
    "name": "Fannie Mae Dees Park",
    "city": "Nashville",
    "state": "TN",
    "zip": "",
    "location": ["36.141213", "-86.802777"],
    "address": "2400 Blakemore Ave"
},{
    "number": "36",
    "name": "Flora Wilson Community Park",
    "city": "Nashville",
    "state": "TN",
    "zip": "",
    "location": ["36.16784292800048", "-86.77815577199965"],
    "address": "1000 15th Ave S"
},{
    "number": "37",
    "name": "Fort Nashborough",
    "city": "Nashville",
    "state": "TN",
    "zip": "",
    "location": ["36.16399329900048", "-86.77543807099966"],
    "address": "170 1st Ave N"
},{
    "number": "38",
    "name": "Fort Negley",
    "city": "Nashville",
    "state": "TN",
    "zip": "",
    "location": ["36.142733559000476", "-86.77586949799968"],
    "address": "1100 Fort Negley Blvd"
},{
    "number": "39",
    "name": "Fred Douglas Park",
    "city": "Nashville",
    "state": "TN",
    "zip": "",
    "location": ["36.177111", "-86.763317"],
    "address": "210 N 7th St"
},{
    "number": "40",
    "name": "Gale Lane Community Park",
    "city": "Nashville",
    "state": "TN",
    "zip": "",
    "location": ["36.11681134300045", "-86.78717930199969"],
    "address": "1001 Gale Lane"
},{
    "number": "41",
    "name": "Granbery Park",
    "city": "Nashville",
    "state": "TN",
    "zip": "",
    "location": ["36.046541", "-86.752967"],
    "address": "5501 Hill Rd"
},{
    "number": "42",
    "name": "Grassmere / Nashville Zoo",
    "city": "Nashville",
    "state": "TN",
    "zip": "",
    "location": ["36.09053885500049", "-86.73421064099966"],
    "address": "3777 Nolensville Pike"
},{
  "number": "43",
  "name": "Green Hills Park",
  "city": "Nashville",
  "state": "TN",
  "zip": "",
  "location": ["36.094200", "-86.804607"],
  "address": "1200 Lone Oak Rd"
},{
  "number": "44",
  "name": "H.G. Hill Park",
  "city": "Nashville",
  "state": "TN",
  "zip": "",
  "location": ["36.13532730300045", "-86.88656005799965"],
  "address": "6710 Charlotte Pike"
},{
  "number": "45",
  "name": "Hadley Park",
  "city": "Nashville",
  "state": "TN",
  "zip": "",
  "location": ["36.166715", "-86.820489"],
  "address": "1037 28th Ave North"
},{
  "number": "46",
  "name": "Hamilton Creek Park",
  "city": "Nashville",
  "state": "TN",
  "zip": "",
  "location": ["36.107193", "-86.629635"],
  "address": "2901 Bell Rd"
},{
  "number": "47",
  "name": "Harpeth Knoll Park",
  "city": "Nashville",
  "state": "TN",
  "zip": "",
  "location": ["36.059275", "-86.937998"],
  "address": "708 Goodpasture Terrace"
},{
  "number": "48",
  "name": "Harpeth River Park",
  "city": "Nashville",
  "state": "TN",
  "zip": "",
  "location": ["36.077868", "-86.959838"],
  "address": "7820 Coley Davis Rd"
},{
  "number": "49",
  "name": "Heartland Park",
  "city": "Nashville",
  "state": "TN",
  "zip": "",
  "location": ["36.187741", "-86.666356"],
  "address": "3101 Heartland Dr"
},{
  "number": "50",
  "name": "Hermitage Park",
  "city": "Nashville",
  "state": "TN",
  "zip": "",
  "location": ["36.17762626400048", "-86.61608349499966"],
  "address": "3720JamesKayLane"
},{
  "number": "51",
  "name": "Hope Gardens Park",
  "city": "Nashville",
  "state": "TN",
  "zip": "",
  "location": ["36.170865", "-86.794745"],
  "address": "1009 Phillips St"
},{
  "number": "52",
  "name": "Isaac Litton School Park",
  "city": "Nashville",
  "state": "TN",
  "zip": "",
  "location": ["36.228195", "-86.724470"],
  "address": "4500 Gallatin Pike"
},{
  "number": "53",
  "name": "J.C. Napier Park",
  "city": "Nashville",
  "state": "TN",
  "zip": "",
  "location": ["36.15032192700045", "-86.75694893599967"],
  "address": "67 Fairfield Ave"
},{
  "number": "54",
  "name": "Joelton Park",
  "city": "Nashville",
  "state": "TN",
  "zip": "",
  "location": ["36.317353", "-86.870347"],
  "address": "21 Joelton Community Center Rd"
},{
  "number": "55",
  "name": "Joseph Brown Mullins Park",
  "city": "Nashville",
  "state": "TN",
  "zip": "",
  "location": ["36.20912422800046", "-86.85080845299967"],
  "address": "4297 Drake Wood Lane"
},{
  "number": "56",
  "name": "Kirkpatrick Park",
  "city": "Nashville",
  "state": "TN",
  "zip": "",
  "location": ["36.167343", "-86.752100"],
  "address": "1000 Sevier St"
},{
  "number": "57",
  "name": "Lakewood Park",
  "city": "Nashville",
  "state": "TN",
  "zip": "",
  "location": ["36.23864579500048", "-86.63484326099967"],
  "address": "319 Pitts Ave"
},{
  "number": "58",
  "name": "Lock One Park",
  "city": "Nashville",
  "state": "TN",
  "zip": "",
  "location": ["36.199391", "-86.787406"],
  "address": "1530 Lock Rd"
},{
  "number": "59",
  "name": "Lock Two Park",
  "city": "Nashville",
  "state": "TN",
  "zip": "",
  "location": ["36.239196", "-86.700730"],
  "address": "Lock 2 Rd"
},{
  "number": "60",
  "name": "Lockeland Springs Park",
  "city": "Nashville",
  "state": "TN",
  "zip": "",
  "location": ["36.17676268600047", "-86.73715389899968"],
  "address": "1810 Woodland St"
},{
  "number": "61",
  "name": "Louise and Rebecca Dudley Park",
  "city": "Nashville",
  "state": "TN",
  "zip": "",
  "location": ["36.143886", "-86.765354"],
  "address": "305 Chestnut St"
},{
  "number": "62",
  "name": "Madison Park",
  "city": "Nashville",
  "state": "TN",
  "zip": "",
  "location": ["36.267844", "-86.702801"],
  "address": "510 North Dupont Ave"
},{
  "number": "63",
  "name": "McCabe Park",
  "city": "Nashville",
  "state": "TN",
  "zip": "",
  "location": ["36.137845", "-86.847436"],
  "address": "4601 Murphy Rd"
},{
  "number": "64",
  "name": "McFerrin Park",
  "city": "Nashville",
  "state": "TN",
  "zip": "",
  "location": ["36.182700", "-86.768613"],
  "address": "310 Grace Street"
},{
  "number": "65",
  "name": "McKissack Park",
  "city": "Nashville",
  "state": "TN",
  "zip": "",
  "location": ["36.157479", "-86.818642"],
  "address": "28th Ave and Torbett St"
},{
  "number": "66",
  "name": "Metro Soccer Complex",
  "city": "Nashville",
  "state": "TN",
  "zip": "",
  "location": ["36.102128302000494", "-86.67510268099966"],
  "address": "1266 Donelson Pike"
},{
  "number": "67",
  "name": "Mildred Shute Minipark",
  "city": "Nashville",
  "state": "TN",
  "zip": "",
  "location": ["36.151600", "-86.758977"],
  "address": "73 Maury Stx"
},{
  "number": "68",
  "name": "Mill Creek Park",
  "city": "Nashville",
  "state": "TN",
  "zip": "",
  "location": ["36.014088", "-86.682587"],
  "address": "6036 Culbertson Rd"
},{
  "number": "69",
  "name": "Monroe Street Playground",
  "city": "Nashville",
  "state": "TN",
  "zip": "",
  "location": ["36.173593206000476", "-86.79895401999966"],
  "address": "1043 Monroe Street"
},{
  "number": "70",
  "name": "Morgan Park",
  "city": "Nashville",
  "state": "TN",
  "zip": "",
  "location": ["36.18075770000047", "-86.79097346899965"],
  "address": "411 Hume Street"
},{
  "number": "71",
  "name": "Oakwood Park",
  "city": "Nashville",
  "state": "TN",
  "zip": "",
  "location": ["36.214988", "-86.750029"],
  "address": "2572 Bethwood Drive"
},{
  "number": "72",
  "name": "OHUD Arts Center",
  "city": "Nashville",
  "state": "TN",
  "zip": "",
  "location": ["36.256637", "-86.652732"],
  "address": "1308 Fuller St"
},{
  "number": "73",
  "name": "OHUD Community Center",
  "city": "Nashville",
  "state": "TN",
  "zip": "",
  "location": ["36.26411762900045", "-86.64961063399966"],
  "address": "1050 Donelson Ave"
},{
  "number": "74",
  "name": "OHUD Large Baseball Field",
  "city": "Nashville",
  "state": "TN",
  "zip": "",
  "location": ["36.210510068000474", "-86.71628223299967"],
  "address": "1700 Golf Club Rd"
},{
  "number": "75",
  "name": "Old Hickory Cemetery",
  "city": "Nashville",
  "state": "TN",
  "zip": "",
  "location": ["36.263932", "-86.651500"],
  "address": "1207 Donelson Ave"
},{
  "number": "76",
  "name": "Owen Bradley Park",
  "city": "Nashville",
  "state": "TN",
  "zip": "",
  "location": ["36.151601", "-86.791997"],
  "address": "1 Music Square E"
},
{
  "number": "77",
  "name": "Paradise Ridge Park",
  "city": "Nashville",
  "state": "TN",
  "zip": "",
  "location": ["36.337380", "-86.859674"],
  "address": "3000 Morgan Rd"
},
{
  "number": "78",
  "name": "Paragon Mills Park",
  "city": "Nashville",
  "state": "TN",
  "zip": "",
  "location": ["36.095111", "-86.714802"],
  "address": "465 Benita Dr"
},{
  "number": "79",
  "name": "Parkwood Park",
  "city": "Nashville",
  "state": "TN",
  "zip": "",
  "location": ["36.235050", "-86.771357"],
  "address": "3220 Vailview Dr"
},{
  "number": "80",
  "name": "Parmer Park",
  "city": "Nashville",
  "state": "TN",
  "zip": "",
  "location": ["36.102203", "-86.857034"],
  "address": "578 Leake Ave"
},{
  "number": "81",
  "name": "Percy Warner Park",
  "city": "Nashville",
  "state": "TN",
  "zip": "",
  "location": ["36.16784292800048", "-86.77815577199965"],
  "address": "7311 Hwy 100"
},{
  "number": "82",
  "name": "Potters Field",
  "city": "Nashville",
  "state": "TN",
  "zip": "",
  "location": ["36.16784292800048", "-86.77815577199965"],
  "address": "2301 Metro Center Blvd."
},{
  "number": "83",
  "name": "Providence Park",
  "city": "Nashville",
  "state": "TN",
  "zip": "",
  "location": ["36.091114", "-86.706567"],
  "address": "4170 Providence Park Ln"
},{
  "number": "84",
  "name": "Public Square Park",
  "city": "Nashville",
  "state": "TN",
  "zip": "",
  "location": ["36.16710296600047", "-86.77953748799968"],
  "address": "10 Public Square"
},{
  "number": "85",
  "name": "R.H. Boyd-Preston Taylor Park",
  "city": "Nashville",
  "state": "TN",
  "zip": "",
  "location": ["36.163330", "-86.835045"],
  "address": "3900 Clifton Ave Nashville"
},{
  "number": "86",
  "name": "Rachel's Walk",
  "city": "Nashville",
  "state": "TN",
  "zip": "",
  "location": ["36.256408", "-86.646566"],
  "address": "801 Fourteenth St"
},{
  "number": "87",
  "name": "Reservoir Park",
  "city": "Nashville",
  "state": "TN",
  "zip": "",
  "location": ["36.252993655000466", "-86.71312459699965"],
  "address": "824 Argyle Ave"
},{
  "number": "88",
  "name": "Richard W. Hartman Park",
  "city": "Nashville",
  "state": "TN",
  "zip": "",
  "location": ["36.208036", "-86.827367"],
  "address": "2801 Tucker Rd"
},{
  "number": "89",
  "name": "Richland Park",
  "city": "Nashville",
  "state": "TN",
  "zip": "",
  "location": ["36.15214354900047", "-86.84283876299969"],
  "address": "4601 Charlotte Pike"
},{
  "number": "90",
  "name": "Riverfront Park",
  "city": "Nashville",
  "state": "TN",
  "zip": "",
  "location": ["36.162436", "-86.774026"],
  "address": "100 1st Ave South"
},{
  "number": "91",
  "name": "Sally Beaman",
  "city": "Nashville",
  "state": "TN",
  "zip": "",
  "location": ["36.109904", "-86.809103"],
  "address": "3701 Benham Avex"
},{
  "number": "92",
  "name": "Seven Oaks Park",
  "city": "Nashville",
  "state": "TN",
  "zip": "",
  "location": ["36.107106376000445", "-86.70382698199967"],
  "address": "3474 McGavock Pike"
},{
  "number": "93",
  "name": "Sevier Park",
  "city": "Nashville",
  "state": "TN",
  "zip": "",
  "location": ["36.119345", "-86.787399"],
  "address": "3021 Lealand Lanex"
},{
  "number": "94",
  "name": "Shelby Bottoms Park",
  "city": "Nashville",
  "state": "TN",
  "zip": "",
  "location": ["36.16461575700049", "-86.73559441399965"],
  "address": "1900 Davidson Street"
},{
  "number": "95",
  "name": "Shelby Park",
  "city": "Nashville",
  "state": "TN",
  "zip": "",
  "location": ["36.169844157000455", "-86.73591756699966"],
  "address": "South 20th Stat Shelby Ave"
},{
  "number": "96",
  "name": "Shelby Walk Park",
  "city": "Nashville",
  "state": "TN",
  "zip": "",
  "location": ["36.170566", "-86.746338"],
  "address": "1400 Shelby Ave"
},{
  "number": "97",
  "name": "SouthIng lewood Park",
  "city": "Nashville",
  "state": "TN",
  "zip": "",
  "location": ["35.988518", "-86.609243"],
  "address": "1624 Moore Street"
},{
  "number": "98",
  "name": "St.BernardPark",
  "city": "Nashville",
  "state": "TN",
  "zip": "",
  "location": ["36.131304", "-86.801495"],
  "address": "21st Aveand Bernard Ave"
},{
  "number": "99",
  "name": "Stone Hall Park",
  "city": "Nashville",
  "state": "TN",
  "zip": "",
  "location": ["36.187701", "-86.632646"],
  "address": "1014 Stones River Rd"
},{
  "number": "100",
  "name": "Ted Rhodes Park",
  "city": "Nashville",
  "state": "TN",
  "zip": "",
  "location": ["36.184588", "-86.824773"],
  "address": "1901 Ed Temple Blvd"
},{
  "number": "101",
  "name": "Tom Joy Park",
  "city": "Nashville",
  "state": "TN",
  "zip": "",
  "location": ["36.203803941000444", "-86.76140705299969"],
  "address": "1901 Lischey Ave"
},{
  "number": "102",
  "name": "Tony Rose Park",
  "city": "Nashville",
  "state": "TN",
  "zip": "",
  "location": ["36.149317548000454", "-86.79065723099967"],
  "address": "8 Music Circle East"
},{
  "number": "103",
  "name": "Turner School Park",
  "city": "Nashville",
  "state": "TN",
  "zip": "",
  "location": ["36.108174", "-86.745369"],
  "address": "507 Tanksley Ave"
},{
  "number": "104",
  "name": "Two Rivers Park",
  "city": "Nashville",
  "state": "TN",
  "zip": "",
  "location": ["36.18517436400049", "-86.67650028399964"],
  "address": "3150 McGavock Pike"
},{
  "number": "105",
  "name": "Una Recreation Park",
  "city": "Nashville",
  "state": "TN",
  "zip": "",
  "location": ["36.097419", "-86.640492"],
  "address": "134 Una Recreation Rd"
},{
  "number": "106",
  "name": "Veterans Parks",
  "city": "Nashville",
  "state": "TN",
  "zip": "",
  "location": ["36.26489018600046", "-86.65080389999969"],
  "address": "609 Bryan St"
},{
  "number": "107",
  "name": "Walk of Fame Park",
  "city": "Nashville",
  "state": "TN",
  "zip": "",
  "location": ["36.160384671000486", "-86.77675818499966"],
  "address": "121 4th Ave S"
},{
  "number": "108",
  "name": "Watkins Park",
  "city": "Nashville",
  "state": "TN",
  "zip": "",
  "location": ["36.161768", "-86.800192"],
  "address": "616 17th AveNorth"
},{
  "number": "109",
  "name": "Wentworth-Caldwell Park",
  "city": "Nashville",
  "state": "TN",
  "zip": "",
  "location": ["36.077255", "-86.727819"],
  "address": "4927 Edmondson Pikex"
},{
  "number": "110",
  "name": "West Park",
  "city": "Nashville",
  "state": "TN",
  "zip": "",
  "location": ["36.16328623500044", "-86.86282288699965"],
  "address": "6105 Morrow Road"
},{
  "number": "111",
  "name": "Whites Creek Park",
  "city": "Nashville",
  "state": "TN",
  "zip": "",
  "location": ["36.277554", "-86.819617"],
  "address": "7277 Old Hickory Blvd"
},{
  "number": "112",
  "name": "Whitsett Park",
  "city": "Nashville",
  "state": "TN",
  "zip": "",
  "location": ["36.109626", "-86.730364"],
  "address": "0 Thompson Lane"
},{
  "number": "113",
  "name": "William A. Pitts Park",
  "city": "Nashville",
  "state": "TN",
  "zip": "",
  "location": ["36.057519", "-86.706611"],
  "address": "299 Tusculum Rd"
},{
  "number": "114",
  "name": "William Coleman Park",
  "city": "Nashville",
  "state": "TN",
  "zip": "",
  "location": ["36.111849", "-86.744300"],
  "address": "384 Thompson Ln"
},{
  "number": "115",
  "name": "William Edmondson Park",
  "city": "Nashville",
  "state": "TN",
  "zip": "",
  "location": ["36.158815", "-86.798767"],
  "address": "1700 Charlotte Ave"
},{
  "number": "116",
  "name": "William Whitfield Park",
  "city": "Nashville",
  "state": "TN",
  "zip": "",
  "location": ["36.061995769000475", "-86.74011136899969"],
  "address": "5150 Edmondson Pike"
},{
  "number": "117",
  "name": "Willow Creek Park",
  "city": "Nashville",
  "state": "TN",
  "zip": "",
  "location": ["36.252905", "-86.773282"],
  "address": "1821 Westchester Dr"
},{
  "number": "118",
  "name": "Woodmont Park",
  "city": "Nashville",
  "state": "TN",
  "zip": "",
  "location": ["36.118535", "-86.836103"],
  "address": "912 Estes Rd"
}]























